promptfold_client/__init__.py
promptfold_client/client.py
promptfold_client/models.py
promptfold-1.0.15.dist-info/METADATA
promptfold-1.0.15.dist-info/WHEEL
promptfold-1.0.15.dist-info/top_level.txt
promptfold-1.0.15.dist-info/RECORD
