Metadata-Version: 2.4
Name: promptfold
Version: 1.0.15
Summary: Python client for PromptFold API - optimize prompts with PromptFold
Author-email: PromptFold Team <team@promptfold.com>
License: MIT
Project-URL: Homepage, https://github.com/paulcrowley/promptfold
Project-URL: Repository, https://github.com/paulcrowley/promptfold
Project-URL: Issues, https://github.com/paulcrowley/promptfold/issues
Keywords: promptfold,optimization,api,client
Classifier: Development Status :: 4 - Beta
Classifier: Intended Audience :: Developers
Classifier: License :: OSI Approved :: MIT License
Classifier: Programming Language :: Python :: 3
Classifier: Programming Language :: Python :: 3.8
Classifier: Programming Language :: Python :: 3.9
Classifier: Programming Language :: Python :: 3.10
Classifier: Programming Language :: Python :: 3.11
Classifier: Programming Language :: Python :: 3.12
Classifier: Topic :: Software Development :: Libraries :: Python Modules
Classifier: Topic :: Scientific/Engineering :: Artificial Intelligence
Classifier: Topic :: Text Processing :: Linguistic
Requires-Python: >=3.8
Requires-Dist: requests>=2.25.0
Provides-Extra: dev
Requires-Dist: pytest>=6.0; extra == "dev"
Requires-Dist: black>=21.0; extra == "dev"
Requires-Dist: flake8>=3.8; extra == "dev"
